Metadata-Version: 2.1
Name: bolid-selenium-test
Version: 1.5
Summary: SeleniumMtehods
Home-page: UNKNOWN
Author-email: sbolid-test@yandex.ru
License: UNKNOWN
Platform: UNKNOWN
